citrascope/__init__.py
citrascope/__main__.py
citrascope/citra_scope_daemon.py
citrascope/constants.py
citrascope/api/abstract_api_client.py
citrascope/api/citra_api_client.py
citrascope/hardware/abstract_astro_hardware_adapter.py
citrascope/hardware/adapter_registry.py
citrascope/hardware/direct_hardware_adapter.py
citrascope/hardware/filter_sync.py
citrascope/hardware/indi_adapter.py
citrascope/hardware/kstars_dbus_adapter.py
citrascope/hardware/kstars_scheduler_template.esl
citrascope/hardware/kstars_sequence_template.esq
citrascope/hardware/nina_adv_http_adapter.py
citrascope/hardware/nina_adv_http_survey_template.json
citrascope/hardware/devices/__init__.py
citrascope/hardware/devices/abstract_hardware_device.py
citrascope/hardware/devices/device_registry.py
citrascope/hardware/devices/camera/__init__.py
citrascope/hardware/devices/camera/abstract_camera.py
citrascope/hardware/devices/camera/rpi_hq_camera.py
citrascope/hardware/devices/camera/usb_camera.py
citrascope/hardware/devices/camera/ximea_camera.py
citrascope/hardware/devices/filter_wheel/__init__.py
citrascope/hardware/devices/filter_wheel/abstract_filter_wheel.py
citrascope/hardware/devices/focuser/__init__.py
citrascope/hardware/devices/focuser/abstract_focuser.py
citrascope/hardware/devices/mount/__init__.py
citrascope/hardware/devices/mount/abstract_mount.py
citrascope/logging/__init__.py
citrascope/logging/_citrascope_logger.py
citrascope/logging/web_log_handler.py
citrascope/settings/__init__.py
citrascope/settings/citrascope_settings.py
citrascope/settings/settings_file_manager.py
citrascope/tasks/runner.py
citrascope/tasks/task.py
citrascope/tasks/scope/base_telescope_task.py
citrascope/tasks/scope/static_telescope_task.py
citrascope/tasks/scope/tracking_telescope_task.py
citrascope/time/__init__.py
citrascope/time/time_health.py
citrascope/time/time_monitor.py
citrascope/time/time_sources.py
citrascope/web/__init__.py
citrascope/web/app.py
citrascope/web/server.py
citrascope/web/static/api.js
citrascope-0.8.0.dist-info/METADATA
citrascope-0.8.0.dist-info/WHEEL
citrascope-0.8.0.dist-info/entry_points.txt
citrascope-0.8.0.dist-info/licenses/LICENSE
citrascope-0.8.0.dist-info/RECORD
