Metadata-Version: 2.4
Name: citrascope
Version: 0.8.0
Summary: Remotely control a telescope while it polls for tasks, collects and edge processes data, and delivers results and data for further processing.
Project-URL: Homepage, https://citra.space
Project-URL: Documentation, https://docs.citra.space/citrascope/
Project-URL: Repository, https://github.com/citra-space/citrascope
Project-URL: Issues, https://github.com/citra-space/citrascope/issues
Project-URL: Changelog, https://github.com/citra-space/citrascope/releases
Author-email: Patrick McDavid <patrick@citra.space>
License: MIT
License-File: LICENSE
Keywords: INDI,KStars,NINA,astronomy,astrophotography,imaging,observatory,remote-telescope,telescope,telescope-control
Classifier: Development Status :: 4 - Beta
Classifier: Intended Audience :: Science/Research
Classifier: License :: OSI Approved :: MIT License
Classifier: Operating System :: OS Independent
Classifier: Programming Language :: Python :: 3
Classifier: Programming Language :: Python :: 3.10
Classifier: Programming Language :: Python :: 3.11
Classifier: Programming Language :: Python :: 3.12
Classifier: Topic :: Scientific/Engineering :: Astronomy
Classifier: Topic :: System :: Hardware :: Hardware Drivers
Requires-Python: <3.13,>=3.10
Requires-Dist: click
Requires-Dist: fastapi>=0.104.0
Requires-Dist: httpx
Requires-Dist: ntplib>=0.4.0
Requires-Dist: platformdirs>=4.0.0
Requires-Dist: python-dateutil
Requires-Dist: requests
Requires-Dist: skyfield
Requires-Dist: uvicorn[standard]>=0.24.0
Requires-Dist: websockets>=12.0
Provides-Extra: all
Requires-Dist: dbus-python; extra == 'all'
Requires-Dist: pixelemon; extra == 'all'
Requires-Dist: plotly; extra == 'all'
Requires-Dist: pyindi-client; extra == 'all'
Provides-Extra: all-hardware
Requires-Dist: cv2-enumerate-cameras>=1.0.0; extra == 'all-hardware'
Requires-Dist: opencv-python>=4.8.0; extra == 'all-hardware'
Requires-Dist: picamera2>=0.3.12; extra == 'all-hardware'
Requires-Dist: pixelemon; extra == 'all-hardware'
Requires-Dist: plotly; extra == 'all-hardware'
Requires-Dist: pyindi-client; extra == 'all-hardware'
Requires-Dist: ximea-api>=1.0.0; extra == 'all-hardware'
Provides-Extra: build
Requires-Dist: build; extra == 'build'
Provides-Extra: deploy
Requires-Dist: twine; extra == 'deploy'
Provides-Extra: dev
Requires-Dist: black; extra == 'dev'
Requires-Dist: bump-my-version; extra == 'dev'
Requires-Dist: flake8; extra == 'dev'
Requires-Dist: flake8-pytest-style; extra == 'dev'
Requires-Dist: isort; extra == 'dev'
Requires-Dist: mockito; extra == 'dev'
Requires-Dist: mypy; extra == 'dev'
Requires-Dist: pre-commit; extra == 'dev'
Requires-Dist: pytest; extra == 'dev'
Requires-Dist: pytest-cov; extra == 'dev'
Requires-Dist: types-python-dateutil; extra == 'dev'
Provides-Extra: indi
Requires-Dist: pixelemon; extra == 'indi'
Requires-Dist: plotly; extra == 'indi'
Requires-Dist: pyindi-client; extra == 'indi'
Provides-Extra: kstars
Requires-Dist: dbus-python; extra == 'kstars'
Provides-Extra: rpi
Requires-Dist: picamera2>=0.3.12; extra == 'rpi'
Provides-Extra: test
Requires-Dist: mockito; extra == 'test'
Requires-Dist: pytest; extra == 'test'
Requires-Dist: pytest-cov; extra == 'test'
Provides-Extra: usb-camera
Requires-Dist: cv2-enumerate-cameras>=1.0.0; extra == 'usb-camera'
Requires-Dist: opencv-python>=4.8.0; extra == 'usb-camera'
Provides-Extra: ximea
Requires-Dist: ximea-api>=1.0.0; extra == 'ximea'
